jproperties.py
jproperties3-0.5.2.dist-info/DESCRIPTION.rst
jproperties3-0.5.2.dist-info/METADATA
jproperties3-0.5.2.dist-info/RECORD
jproperties3-0.5.2.dist-info/WHEEL
jproperties3-0.5.2.dist-info/metadata.json
jproperties3-0.5.2.dist-info/top_level.txt
